Metadata-Version: 2.1
Name: captcha-solution
Version: 0.0.5
Summary: Universal interface to captcha solving services
Home-page: https://github.com/lorien/captcha_solution
Author: Gregory Petukhov
Author-email: lorien@lorien.name
Maintainer: Gregory Petukhov
Maintainer-email: lorien@lorien.name
License: MIT
Download-URL: https://github.com/lorien/captcha_solver/releases
Keywords: captcha antigate rucaptcha 2captcha
Platform: UNKNOWN
Classifier: Programming Language :: Python
Classifier: Programming Language :: Python :: 3.5
Classifier: Programming Language :: Python :: 3.6
Classifier: Programming Language :: Python :: 3.7
Classifier: Programming Language :: Python :: 3.8
Classifier: Programming Language :: Python :: Implementation :: CPython
Classifier: License :: OSI Approved :: MIT License
Classifier: Topic :: Software Development :: Libraries :: Python Modules
